Workbook

Sheet 使い方
B2: 人材開発支援助成金／事業展開等リスキリング支援コース
B3: 【定額制サービスによる訓練】 複数社管理チェックシート
B5: このファイルの目的 | C5: 複数の会社のリスキリング助成金（定額制サービス）の手続きを、担当者1人が期限を落とさずに回すためのシート。
B6: シートの構成 | C6: ①使い方（このシート）／②期限一覧（会社ごとの期限を自動計算）／③逆算スケジュール（いつ何をするか）／④チェックリスト（会社ごとに49項目）／⑤やってはいけないこと
B8: 入力するところ | C8: 黄色い背景・青い文字のセルだけです。白いセルは計算式が入っているので触らないでください。
B9: 最初にやること | C9: 「期限一覧」シートの3行目（記入例）を見てから、4行目以降にご自分の会社を書いてください。記入例の行は消しても構いません。
B11: 期限の計算ルール
B12: 計画届の提出期限 | C12: 契約開始日の1か月前の同じ日（例：4月1日契約開始→3月1日まで）。通常訓練の「6か月前〜1か月前」とは違います。同じ日が無い月は、その月の末日で計算しています（末日の扱いは一次情報で未確認）。
B13: 訓練の実施期間 | C13: 最長1年。契約終了日が空欄のときは「契約開始日から1年間」として計算します。1年を超える契約は1年ごとに申請が必要です（このシートは1年目のみ計算します）。
B14: 支給申請の期限 | C14: 訓練終了日の翌日から2か月以内＝訓練終了日の2か月後の同じ日（例：3月31日終了→5月31日まで）。
B15: 郵送するとき | C15: 到着日が提出日です。期限当日の消印では間に合いません。
B16: 書類の保管 | C16: 支給決定後5年間。会計検査院の検査対象になる場合があります。
B18: 特に落としやすい3点
B19: 受講予定者は後から追加できない | C19: 計画届（様式第3-2号）に書いていない人が受講しても助成対象外です。受講させる予定の全員を最初に届け出てください。
B20: 1人あたり10時間以上 | C20: 修了した訓練の「標準学習時間」の合計が10時間以上の人だけが対象です。標準学習時間は訓練機関が定めた時間数で、実際の動画視聴時間ではありません。趣味・教養の講座は数えません。
B21: 業務命令として労働時間内に | C21: 従業員が自分から時間外に受講した時間は10時間に数えられません。社長・管理職から業務命令として指示し、就業時間内に行わせてください。受講中は通常の賃金が必要です。
B23: ⚠ 使う前に必ず読んでください（3士業の点検で出た重大な指摘）
B24: ① この資料より新しい版がある可能性が高い | C24: 検索では「令和8年8月3日改正版」の存在が確認されました（原文は未読）。2026年8月3日以降に計画届を出す案件には、この資料の前提が当てはまらないおそれがあります。訓練機関との契約・申込みが2026年8月2日以前なら旧基準という経過措置があるとされますが、日付の分かる契約書等での証明が要ります。【必ず一次確認】
B25: ② 経費助成には上限額があります | C25: この資料には上限額が書かれていません。「契約額×75%」で経営者に提示すると期待値を誤らせます。定額制サービスには1人1月あたりの上限があるとされますが、金額と、それが助成額の上限なのか対象経費の上限なのか（＝75%を掛ける順序）は確認できていません。結果が倍違います。【必ず一次確認】
B26: ③ 支給申請の回数にも上限があります | C26: 1労働者1年度あたり3回まで、eラーニングは1回までとする情報があります。定額制サービスにこの回数制限が及ぶかは情報が割れています。複数回の申請を前提に動くと、2回目以降が丸ごと不支給になり得ます。【必ず一次確認】
B27: ④ 汎用的なAI・DX・GX研修は対象外になった可能性 | C27: 訓練名に「AI」「DX」「GX」が付いているだけでは不可で、その人の職務に直接必要であることが求められるようになったとされます。定額制は「受け放題」のため汎用講座が主力になりがちです。DX・GX型ではなく事業展開型で書き切るほうが安全です。【必ず一次確認】
B28: ⑤ お金は後払いです | C28: 訓練費は全額を先に会社が払います。助成金が入るのは支給決定の後です。「申請から2か月で入る」ではありません。資金繰り表に入金予定として載せるときは注意してください。
B29: ⑥ 欠格事由がこの資料に書かれていません | C29: 「支給申請日の前日から1年前までの間に労働関係法令違反があった事業主は不支給」が実務で一番効きます。労基署の是正勧告を受けた会社が混じっていると、計画届が通っても支給申請で落ちます。「事前スクリーニング」シートで各社を確認してください。
B30: ⑦ 認定経営革新等支援機関の確認が要るかもしれません | C30: 事業展開等実施計画について、認定経営革新等支援機関（中小企業診断士・税理士・金融機関等）の確認が必要になったとする情報があります。事実なら工程が1本増え、「契約初日の1か月前」の期限設計が破綻します。【必ず一次確認】
B31: ⑧ 契約は各社がそれぞれ結んでください | C31: 親会社が一括契約して子会社に請求しない形にすると、(a)子会社が自社の支払を証明できず助成対象外になるおそれ (b)親会社で寄附金と認定され損金にならない、の両方が起きます。100%グループでも解消しません。契約してからでは戻せません。
B32: ⑨ 助成金には税金がかかります | C32: この助成金は経費助成なので圧縮記帳（課税の繰り延べ）が使えません。受給額はそのまま課税所得を押し上げます。「税務の注意」シートを見てください。
B34: この資料の出所と注意
B35: 出所 | C35: 紙資料「計画書提出から支給申請まで 段取りガイド&チェックリスト」（自称根拠＝厚生労働省 詳細パンフレット・支給要項 R8.5.14版）を 2026年9月15日 に読み取って作成。
B36: 点検の状況 | C36: 社会保険労務士・税理士・中小企業診断士の3つの観点でAIによる点検を行いましたが、厚生労働省・国税庁のサイトへの接続がこの環境で遮断されており、条文・パンフレットの原文は1件も読めていません。上の①〜⑨は検索結果の要約に基づく指摘です。
B37: 未確認であること | C37: したがって、この資料の数値・要件は厚生労働省の一次情報と突き合わせが済んでいません。提出前に必ず管轄の都道府県労働局またはハローワークで最新の支給要領・パンフレットを確認してください。
B38: 有資格者の確認について | C38: 実在の社会保険労務士・税理士・中小企業診断士による確認は受けていません。「社労士監修」等の表示はしていません。最終確認と提出は社会保険労務士にご相談ください。
B39: 金額について | C39: 経費助成率（中小75%／大企業60%）は資料の記載です。上限額・加算・対象外講座の除外は反映していないため、実際の支給額とは異なります。
B40: 書体について | C40: BIZ UDPゴシックで作っています。お使いのパソコンに無い場合は別の書体で表示されますが、中身は変わりません。

Sheet 期限一覧
A1: 期限一覧 黄色いセルだけ入力してください（白いセルは自動計算）
A2: 会社名 | B2: 管轄労働局 | C2: 定額制サービス名 | D2: 企業区分 | E2: 受講予定者数 | F2: 契約開始日 | G2: 契約終了日 (空欄=1年) | H2: ★計画届の 提出期限 | I2: 計画届まで あと何日 | J2: 訓練終了日 | K2: ★支給申請の 期限 | L2: 申請まで あと何日 | M2: いま何をする時期か | N2: 計画届 提出済 | O2: 支給申請 提出済
A3: 株式会社○○（記入例） | B3: 東京労働局 | C3: ○○ラーニング 年間プラン | D3: 中小企業 | E3: 12 | F3: 2027/04/01 | H3: =IF($F3="","",EDATE($F3,-1)) | I3: =IF($H3="","",$H3-TODAY()) | J3: =IF($F3="","",IF($G3="",EDATE($F3,12)-1,MIN($G3,EDATE($F3,12)-1))) | K3: =IF($J3="","",EDATE($J3,2)) | L3: =IF($K3="","",$K3-TODAY()) | M3: =IF($F3="","",IF($O3="済","完了",IF(AND($N3<>"済",$I3<0),"計画届の期限を過ぎています",IF($N3<>"済","計画届の準備（あと"&$I3&"日）",IF(TODAY()<$F3,"訓練開始待ち",IF(TODAY()<=$J3,"訓練実施中（受講進捗を月1回確認）",IF($L3<0,"支給申請の期限を過ぎています","支給申請の準備（あと"&$L3&"日）")))))))
H4: =IF($F4="","",EDATE($F4,-1)) | I4: =IF($H4="","",$H4-TODAY()) | J4: =IF($F4="","",IF($G4="",EDATE($F4,12)-1,MIN($G4,EDATE($F4,12)-1))) | K4: =IF($J4="","",EDATE($J4,2)) | L4: =IF($K4="","",$K4-TODAY()) | M4: =IF($F4="","",IF($O4="済","完了",IF(AND($N4<>"済",$I4<0),"計画届の期限を過ぎています",IF($N4<>"済","計画届の準備（あと"&$I4&"日）",IF(TODAY()<$F4,"訓練開始待ち",IF(TODAY()<=$J4,"訓練実施中（受講進捗を月1回確認）",IF($L4<0,"支給申請の期限を過ぎています","支給申請の準備（あと"&$L4&"日）")))))))
H5: =IF($F5="","",EDATE($F5,-1)) | I5: =IF($H5="","",$H5-TODAY()) | J5: =IF($F5="","",IF($G5="",EDATE($F5,12)-1,MIN($G5,EDATE($F5,12)-1))) | K5: =IF($J5="","",EDATE($J5,2)) | L5: =IF($K5="","",$K5-TODAY()) | M5: =IF($F5="","",IF($O5="済","完了",IF(AND($N5<>"済",$I5<0),"計画届の期限を過ぎています",IF($N5<>"済","計画届の準備（あと"&$I5&"日）",IF(TODAY()<$F5,"訓練開始待ち",IF(TODAY()<=$J5,"訓練実施中（受講進捗を月1回確認）",IF($L5<0,"支給申請の期限を過ぎています","支給申請の準備（あと"&$L5&"日）")))))))
H6: =IF($F6="","",EDATE($F6,-1)) | I6: =IF($H6="","",$H6-TODAY()) | J6: =IF($F6="","",IF($G6="",EDATE($F6,12)-1,MIN($G6,EDATE($F6,12)-1))) | K6: =IF($J6="","",EDATE($J6,2)) | L6: =IF($K6="","",$K6-TODAY()) | M6: =IF($F6="","",IF($O6="済","完了",IF(AND($N6<>"済",$I6<0),"計画届の期限を過ぎています",IF($N6<>"済","計画届の準備（あと"&$I6&"日）",IF(TODAY()<$F6,"訓練開始待ち",IF(TODAY()<=$J6,"訓練実施中（受講進捗を月1回確認）",IF($L6<0,"支給申請の期限を過ぎています","支給申請の準備（あと"&$L6&"日）")))))))
H7: =IF($F7="","",EDATE($F7,-1)) | I7: =IF($H7="","",$H7-TODAY()) | J7: =IF($F7="","",IF($G7="",EDATE($F7,12)-1,MIN($G7,EDATE($F7,12)-1))) | K7: =IF($J7="","",EDATE($J7,2)) | L7: =IF($K7="","",$K7-TODAY()) | M7: =IF($F7="","",IF($O7="済","完了",IF(AND($N7<>"済",$I7<0),"計画届の期限を過ぎています",IF($N7<>"済","計画届の準備（あと"&$I7&"日）",IF(TODAY()<$F7,"訓練開始待ち",IF(TODAY()<=$J7,"訓練実施中（受講進捗を月1回確認）",IF($L7<0,"支給申請の期限を過ぎています","支給申請の準備（あと"&$L7&"日）")))))))
H8: =IF($F8="","",EDATE($F8,-1)) | I8: =IF($H8="","",$H8-TODAY()) | J8: =IF($F8="","",IF($G8="",EDATE($F8,12)-1,MIN($G8,EDATE($F8,12)-1))) | K8: =IF($J8="","",EDATE($J8,2)) | L8: =IF($K8="","",$K8-TODAY()) | M8: =IF($F8="","",IF($O8="済","完了",IF(AND($N8<>"済",$I8<0),"計画届の期限を過ぎています",IF($N8<>"済","計画届の準備（あと"&$I8&"日）",IF(TODAY()<$F8,"訓練開始待ち",IF(TODAY()<=$J8,"訓練実施中（受講進捗を月1回確認）",IF($L8<0,"支給申請の期限を過ぎています","支給申請の準備（あと"&$L8&"日）")))))))
H9: =IF($F9="","",EDATE($F9,-1)) | I9: =IF($H9="","",$H9-TODAY()) | J9: =IF($F9="","",IF($G9="",EDATE($F9,12)-1,MIN($G9,EDATE($F9,12)-1))) | K9: =IF($J9="","",EDATE($J9,2)) | L9: =IF($K9="","",$K9-TODAY()) | M9: =IF($F9="","",IF($O9="済","完了",IF(AND($N9<>"済",$I9<0),"計画届の期限を過ぎています",IF($N9<>"済","計画届の準備（あと"&$I9&"日）",IF(TODAY()<$F9,"訓練開始待ち",IF(TODAY()<=$J9,"訓練実施中（受講進捗を月1回確認）",IF($L9<0,"支給申請の期限を過ぎています","支給申請の準備（あと"&$L9&"日）")))))))
H10: =IF($F10="","",EDATE($F10,-1)) | I10: =IF($H10="","",$H10-TODAY()) | J10: =IF($F10="","",IF($G10="",EDATE($F10,12)-1,MIN($G10,EDATE($F10,12)-1))) | K10: =IF($J10="","",EDATE($J10,2)) | L10: =IF($K10="","",$K10-TODAY()) | M10: =IF($F10="","",IF($O10="済","完了",IF(AND($N10<>"済",$I10<0),"計画届の期限を過ぎています",IF($N10<>"済","計画届の準備（あと"&$I10&"日）",IF(TODAY()<$F10,"訓練開始待ち",IF(TODAY()<=$J10,"訓練実施中（受講進捗を月1回確認）",IF($L10<0,"支給申請の期限を過ぎています","支給申請の準備（あと"&$L10&"日）")))))))
H11: =IF($F11="","",EDATE($F11,-1)) | I11: =IF($H11="","",$H11-TODAY()) | J11: =IF($F11="","",IF($G11="",EDATE($F11,12)-1,MIN($G11,EDATE($F11,12)-1))) | K11: =IF($J11="","",EDATE($J11,2)) | L11: =IF($K11="","",$K11-TODAY()) | M11: =IF($F11="","",IF($O11="済","完了",IF(AND($N11<>"済",$I11<0),"計画届の期限を過ぎています",IF($N11<>"済","計画届の準備（あと"&$I11&"日）",IF(TODAY()<$F11,"訓練開始待ち",IF(TODAY()<=$J11,"訓練実施中（受講進捗を月1回確認）",IF($L11<0,"支給申請の期限を過ぎています","支給申請の準備（あと"&$L11&"日）")))))))
H12: =IF($F12="","",EDATE($F12,-1)) | I12: =IF($H12="","",$H12-TODAY()) | J12: =IF($F12="","",IF($G12="",EDATE($F12,12)-1,MIN($G12,EDATE($F12,12)-1))) | K12: =IF($J12="","",EDATE($J12,2)) | L12: =IF($K12="","",$K12-TODAY()) | M12: =IF($F12="","",IF($O12="済","完了",IF(AND($N12<>"済",$I12<0),"計画届の期限を過ぎています",IF($N12<>"済","計画届の準備（あと"&$I12&"日）",IF(TODAY()<$F12,"訓練開始待ち",IF(TODAY()<=$J12,"訓練実施中（受講進捗を月1回確認）",IF($L12<0,"支給申請の期限を過ぎています","支給申請の準備（あと"&$L12&"日）")))))))
H13: =IF($F13="","",EDATE($F13,-1)) | I13: =IF($H13="","",$H13-TODAY()) | J13: =IF($F13="","",IF($G13="",EDATE($F13,12)-1,MIN($G13,EDATE($F13,12)-1))) | K13: =IF($J13="","",EDATE($J13,2)) | L13: =IF($K13="","",$K13-TODAY()) | M13: =IF($F13="","",IF($O13="済","完了",IF(AND($N13<>"済",$I13<0),"計画届の期限を過ぎています",IF($N13<>"済","計画届の準備（あと"&$I13&"日）",IF(TODAY()<$F13,"訓練開始待ち",IF(TODAY()<=$J13,"訓練実施中（受講進捗を月1回確認）",IF($L13<0,"支給申請の期限を過ぎています","支給申請の準備（あと"&$L13&"日）")))))))
H14: =IF($F14="","",EDATE($F14,-1)) | I14: =IF($H14="","",$H14-TODAY()) | J14: =IF($F14="","",IF($G14="",EDATE($F14,12)-1,MIN($G14,EDATE($F14,12)-1))) | K14: =IF($J14="","",EDATE($J14,2)) | L14: =IF($K14="","",$K14-TODAY()) | M14: =IF($F14="","",IF($O14="済","完了",IF(AND($N14<>"済",$I14<0),"計画届の期限を過ぎています",IF($N14<>"済","計画届の準備（あと"&$I14&"日）",IF(TODAY()<$F14,"訓練開始待ち",IF(TODAY()<=$J14,"訓練実施中（受講進捗を月1回確認）",IF($L14<0,"支給申請の期限を過ぎています","支給申請の準備（あと"&$L14&"日）")))))))
H15: =IF($F15="","",EDATE($F15,-1)) | I15: =IF($H15="","",$H15-TODAY()) | J15: =IF($F15="","",IF($G15="",EDATE($F15,12)-1,MIN($G15,EDATE($F15,12)-1))) | K15: =IF($J15="","",EDATE($J15,2)) | L15: =IF($K15="","",$K15-TODAY()) | M15: =IF($F15="","",IF($O15="済","完了",IF(AND($N15<>"済",$I15<0),"計画届の期限を過ぎています",IF($N15<>"済","計画届の準備（あと"&$I15&"日）",IF(TODAY()<$F15,"訓練開始待ち",IF(TODAY()<=$J15,"訓練実施中（受講進捗を月1回確認）",IF($L15<0,"支給申請の期限を過ぎています","支給申請の準備（あと"&$L15&"日）")))))))
A17: ※ 黄色いセルだけ入力してください。★の2つが、過ぎると申請できなくなる厳守の期限です。
A18: ※ 契約期間が1年を超える場合、このシートは1年目だけを計算します。2年目以降は行を分けて、その年の開始日を「契約開始日」に入れてください。
A19: ※ 「あと何日」は、このファイルを開いた日を基準に計算し直されます。

Sheet 逆算スケジュール
A1: 逆算スケジュール 「期限一覧」に入れた会社ごとに、いつ何をするかを自動で出します
A2: ステップ | B2: やること | C2: =IF(期限一覧!A3="","（未入力）",期限一覧!A3) | D2: =IF(期限一覧!A4="","（未入力）",期限一覧!A4) | E2: =IF(期限一覧!A5="","（未入力）",期限一覧!A5) | F2: =IF(期限一覧!A6="","（未入力）",期限一覧!A6) | G2: =IF(期限一覧!A7="","（未入力）",期限一覧!A7) | H2: =IF(期限一覧!A8="","（未入力）",期限一覧!A8) | I2: =IF(期限一覧!A9="","（未入力）",期限一覧!A9) | J2: =IF(期限一覧!A10="","（未入力）",期限一覧!A10) | K2: =IF(期限一覧!A11="","（未入力）",期限一覧!A11) | L2: =IF(期限一覧!A12="","（未入力）",期限一覧!A12) | M2: =IF(期限一覧!A13="","（未入力）",期限一覧!A13) | N2: =IF(期限一覧!A14="","（未入力）",期限一覧!A14)
A3: STEP 0 | B3: 前提条件を整え終える（推進者の選任・計画の周知・様式1-3号） | C3: =IF(期限一覧!$H$3="","",期限一覧!$H$3-14) | D3: =IF(期限一覧!$H$4="","",期限一覧!$H$4-14) | E3: =IF(期限一覧!$H$5="","",期限一覧!$H$5-14) | F3: =IF(期限一覧!$H$6="","",期限一覧!$H$6-14) | G3: =IF(期限一覧!$H$7="","",期限一覧!$H$7-14) | H3: =IF(期限一覧!$H$8="","",期限一覧!$H$8-14) | I3: =IF(期限一覧!$H$9="","",期限一覧!$H$9-14) | J3: =IF(期限一覧!$H$10="","",期限一覧!$H$10-14) | K3: =IF(期限一覧!$H$11="","",期限一覧!$H$11-14) | L3: =IF(期限一覧!$H$12="","",期限一覧!$H$12-14) | M3: =IF(期限一覧!$H$13="","",期限一覧!$H$13-14) | N3: =IF(期限一覧!$H$14="","",期限一覧!$H$14-14)
A4: STEP 1 | B4: ★ 計画届を管轄労働局へ提出する | C4: =IF(期限一覧!$H$3="","",期限一覧!$H$3) | D4: =IF(期限一覧!$H$4="","",期限一覧!$H$4) | E4: =IF(期限一覧!$H$5="","",期限一覧!$H$5) | F4: =IF(期限一覧!$H$6="","",期限一覧!$H$6) | G4: =IF(期限一覧!$H$7="","",期限一覧!$H$7) | H4: =IF(期限一覧!$H$8="","",期限一覧!$H$8) | I4: =IF(期限一覧!$H$9="","",期限一覧!$H$9) | J4: =IF(期限一覧!$H$10="","",期限一覧!$H$10) | K4: =IF(期限一覧!$H$11="","",期限一覧!$H$11) | L4: =IF(期限一覧!$H$12="","",期限一覧!$H$12) | M4: =IF(期限一覧!$H$13="","",期限一覧!$H$13) | N4: =IF(期限一覧!$H$14="","",期限一覧!$H$14)
A5: STEP 2 | B5: 社長通達・受講予定者へ業務命令として周知する | C5: =IF(期限一覧!$F$3="","",期限一覧!$F$3-7) | D5: =IF(期限一覧!$F$4="","",期限一覧!$F$4-7) | E5: =IF(期限一覧!$F$5="","",期限一覧!$F$5-7) | F5: =IF(期限一覧!$F$6="","",期限一覧!$F$6-7) | G5: =IF(期限一覧!$F$7="","",期限一覧!$F$7-7) | H5: =IF(期限一覧!$F$8="","",期限一覧!$F$8-7) | I5: =IF(期限一覧!$F$9="","",期限一覧!$F$9-7) | J5: =IF(期限一覧!$F$10="","",期限一覧!$F$10-7) | K5: =IF(期限一覧!$F$11="","",期限一覧!$F$11-7) | L5: =IF(期限一覧!$F$12="","",期限一覧!$F$12-7) | M5: =IF(期限一覧!$F$13="","",期限一覧!$F$13-7) | N5: =IF(期限一覧!$F$14="","",期限一覧!$F$14-7)
A6: STEP 3 | B6: 定額制サービスの契約開始／訓練開始 | C6: =IF(期限一覧!$F$3="","",期限一覧!$F$3) | D6: =IF(期限一覧!$F$4="","",期限一覧!$F$4) | E6: =IF(期限一覧!$F$5="","",期限一覧!$F$5) | F6: =IF(期限一覧!$F$6="","",期限一覧!$F$6) | G6: =IF(期限一覧!$F$7="","",期限一覧!$F$7) | H6: =IF(期限一覧!$F$8="","",期限一覧!$F$8) | I6: =IF(期限一覧!$F$9="","",期限一覧!$F$9) | J6: =IF(期限一覧!$F$10="","",期限一覧!$F$10) | K6: =IF(期限一覧!$F$11="","",期限一覧!$F$11) | L6: =IF(期限一覧!$F$12="","",期限一覧!$F$12) | M6: =IF(期限一覧!$F$13="","",期限一覧!$F$13) | N6: =IF(期限一覧!$F$14="","",期限一覧!$F$14)
A7: STEP 4 | B7: 各社へ書類準備を依頼／訓練機関へ様式12号を依頼 | C7: =IF(期限一覧!$J$3="","",期限一覧!$J$3-30) | D7: =IF(期限一覧!$J$4="","",期限一覧!$J$4-30) | E7: =IF(期限一覧!$J$5="","",期限一覧!$J$5-30) | F7: =IF(期限一覧!$J$6="","",期限一覧!$J$6-30) | G7: =IF(期限一覧!$J$7="","",期限一覧!$J$7-30) | H7: =IF(期限一覧!$J$8="","",期限一覧!$J$8-30) | I7: =IF(期限一覧!$J$9="","",期限一覧!$J$9-30) | J7: =IF(期限一覧!$J$10="","",期限一覧!$J$10-30) | K7: =IF(期限一覧!$J$11="","",期限一覧!$J$11-30) | L7: =IF(期限一覧!$J$12="","",期限一覧!$J$12-30) | M7: =IF(期限一覧!$J$13="","",期限一覧!$J$13-30) | N7: =IF(期限一覧!$J$14="","",期限一覧!$J$14-30)
A8: STEP 4 | B8: 10時間未満になりそうな人を最終確認し受講を促す | C8: =IF(期限一覧!$J$3="","",期限一覧!$J$3-14) | D8: =IF(期限一覧!$J$4="","",期限一覧!$J$4-14) | E8: =IF(期限一覧!$J$5="","",期限一覧!$J$5-14) | F8: =IF(期限一覧!$J$6="","",期限一覧!$J$6-14) | G8: =IF(期限一覧!$J$7="","",期限一覧!$J$7-14) | H8: =IF(期限一覧!$J$8="","",期限一覧!$J$8-14) | I8: =IF(期限一覧!$J$9="","",期限一覧!$J$9-14) | J8: =IF(期限一覧!$J$10="","",期限一覧!$J$10-14) | K8: =IF(期限一覧!$J$11="","",期限一覧!$J$11-14) | L8: =IF(期限一覧!$J$12="","",期限一覧!$J$12-14) | M8: =IF(期限一覧!$J$13="","",期限一覧!$J$13-14) | N8: =IF(期限一覧!$J$14="","",期限一覧!$J$14-14)
A9: STEP 4 | B9: 訓練終了日 | C9: =IF(期限一覧!$J$3="","",期限一覧!$J$3) | D9: =IF(期限一覧!$J$4="","",期限一覧!$J$4) | E9: =IF(期限一覧!$J$5="","",期限一覧!$J$5) | F9: =IF(期限一覧!$J$6="","",期限一覧!$J$6) | G9: =IF(期限一覧!$J$7="","",期限一覧!$J$7) | H9: =IF(期限一覧!$J$8="","",期限一覧!$J$8) | I9: =IF(期限一覧!$J$9="","",期限一覧!$J$9) | J9: =IF(期限一覧!$J$10="","",期限一覧!$J$10) | K9: =IF(期限一覧!$J$11="","",期限一覧!$J$11) | L9: =IF(期限一覧!$J$12="","",期限一覧!$J$12) | M9: =IF(期限一覧!$J$13="","",期限一覧!$J$13) | N9: =IF(期限一覧!$J$14="","",期限一覧!$J$14)
A10: STEP 5 | B10: 訓練機関へ修了証明・10時間以上の一覧表を依頼 | C10: =IF(期限一覧!$J$3="","",期限一覧!$J$3+1) | D10: =IF(期限一覧!$J$4="","",期限一覧!$J$4+1) | E10: =IF(期限一覧!$J$5="","",期限一覧!$J$5+1) | F10: =IF(期限一覧!$J$6="","",期限一覧!$J$6+1) | G10: =IF(期限一覧!$J$7="","",期限一覧!$J$7+1) | H10: =IF(期限一覧!$J$8="","",期限一覧!$J$8+1) | I10: =IF(期限一覧!$J$9="","",期限一覧!$J$9+1) | J10: =IF(期限一覧!$J$10="","",期限一覧!$J$10+1) | K10: =IF(期限一覧!$J$11="","",期限一覧!$J$11+1) | L10: =IF(期限一覧!$J$12="","",期限一覧!$J$12+1) | M10: =IF(期限一覧!$J$13="","",期限一覧!$J$13+1) | N10: =IF(期限一覧!$J$14="","",期限一覧!$J$14+1)
A11: STEP 5 | B11: 各社から書類を回収し終える | C11: =IF(期限一覧!$J$3="","",期限一覧!$J$3+14) | D11: =IF(期限一覧!$J$4="","",期限一覧!$J$4+14) | E11: =IF(期限一覧!$J$5="","",期限一覧!$J$5+14) | F11: =IF(期限一覧!$J$6="","",期限一覧!$J$6+14) | G11: =IF(期限一覧!$J$7="","",期限一覧!$J$7+14) | H11: =IF(期限一覧!$J$8="","",期限一覧!$J$8+14) | I11: =IF(期限一覧!$J$9="","",期限一覧!$J$9+14) | J11: =IF(期限一覧!$J$10="","",期限一覧!$J$10+14) | K11: =IF(期限一覧!$J$11="","",期限一覧!$J$11+14) | L11: =IF(期限一覧!$J$12="","",期限一覧!$J$12+14) | M11: =IF(期限一覧!$J$13="","",期限一覧!$J$13+14) | N11: =IF(期限一覧!$J$14="","",期限一覧!$J$14+14)
A12: STEP 5 | B12: 支給申請書類一式を完成させる（目標） | C12: =IF(期限一覧!$J$3="","",期限一覧!$J$3+30) | D12: =IF(期限一覧!$J$4="","",期限一覧!$J$4+30) | E12: =IF(期限一覧!$J$5="","",期限一覧!$J$5+30) | F12: =IF(期限一覧!$J$6="","",期限一覧!$J$6+30) | G12: =IF(期限一覧!$J$7="","",期限一覧!$J$7+30) | H12: =IF(期限一覧!$J$8="","",期限一覧!$J$8+30) | I12: =IF(期限一覧!$J$9="","",期限一覧!$J$9+30) | J12: =IF(期限一覧!$J$10="","",期限一覧!$J$10+30) | K12: =IF(期限一覧!$J$11="","",期限一覧!$J$11+30) | L12: =IF(期限一覧!$J$12="","",期限一覧!$J$12+30) | M12: =IF(期限一覧!$J$13="","",期限一覧!$J$13+30) | N12: =IF(期限一覧!$J$14="","",期限一覧!$J$14+30)
A13: STEP 5 | B13: ★ 支給申請書類一式を管轄労働局へ提出する | C13: =IF(期限一覧!$K$3="","",期限一覧!$K$3) | D13: =IF(期限一覧!$K$4="","",期限一覧!$K$4) | E13: =IF(期限一覧!$K$5="","",期限一覧!$K$5) | F13: =IF(期限一覧!$K$6="","",期限一覧!$K$6) | G13: =IF(期限一覧!$K$7="","",期限一覧!$K$7) | H13: =IF(期限一覧!$K$8="","",期限一覧!$K$8) | I13: =IF(期限一覧!$K$9="","",期限一覧!$K$9) | J13: =IF(期限一覧!$K$10="","",期限一覧!$K$10) | K13: =IF(期限一覧!$K$11="","",期限一覧!$K$11) | L13: =IF(期限一覧!$K$12="","",期限一覧!$K$12) | M13: =IF(期限一覧!$K$13="","",期限一覧!$K$13) | N13: =IF(期限一覧!$K$14="","",期限一覧!$K$14)
B15: ※ 日付は「期限一覧」シートの入力から自動で出ています。このシートには入力しません。
B16: ※ ★の2行が厳守の期限です。ほかは、そこから逆算した社内の目標日です。
B17: ※ 契約期間が1年を超える場合は、2年目以降を「期限一覧」に別の行として入れてください。

Sheet チェックリスト
A1: チェックリスト 終わった項目に「レ」と入れてください（会社ごとに列が分かれています）
A2: やること | B2: =IF(期限一覧!A3="","（会社1）",期限一覧!A3) | C2: =IF(期限一覧!A4="","（会社2）",期限一覧!A4) | D2: =IF(期限一覧!A5="","（会社3）",期限一覧!A5) | E2: =IF(期限一覧!A6="","（会社4）",期限一覧!A6) | F2: =IF(期限一覧!A7="","（会社5）",期限一覧!A7) | G2: =IF(期限一覧!A8="","（会社6）",期限一覧!A8) | H2: =IF(期限一覧!A9="","（会社7）",期限一覧!A9) | I2: =IF(期限一覧!A10="","（会社8）",期限一覧!A10)
A3: 進捗（済んだ数 / 全63項目） | B3: =COUNTA(B5:B73)&" / 63" | C3: =COUNTA(C5:C73)&" / 63" | D3: =COUNTA(D5:D73)&" / 63" | E3: =COUNTA(E5:E73)&" / 63" | F3: =COUNTA(F5:F73)&" / 63" | G3: =COUNTA(G5:G73)&" / 63" | H3: =COUNTA(H5:H73)&" / 63" | I3: =COUNTA(I5:I73)&" / 63"
A4: PHASE 0 事前準備（計画届を出す前に済ませる）
A5: □ 【最初に】厚労省サイトで支給要領・パンフレットの最新版を確認した（版数と確認日を記録）
A6: □ 職業能力開発推進者を選任した（辞令・記録あり）
A7: □ 事業内職業能力開発計画を策定した
A8: □ 事業内職業能力開発計画を全従業員に周知した（周知記録あり）
A9: □ 事業展開等実施計画（様式第1-3号）を作成した
A10: □ 定額制サービスの内容を確認した（対象外講座が全講座の5割未満）
A11: □ 労働保険料に未納がないことを確認した（判定は「前年度より前」の保険年度。表現に幅があるため労働局に確認）
A12: □ 「事前スクリーニング」シートで欠格事由を確認した（労働関係法令違反・過去の不正受給・暴力団・性風俗関連）
A13: □ 企業全体（企業単位。事業所単位ではない）で中小企業に当たるかを判定した
A14: □ 定額制サービスの契約を各社がそれぞれ結ぶ形にした（親会社の一括契約にしていない）
A15: □ 定額制サービスのアカウントを雇用保険適用事業所ごとに分けた（訓練機関が事業所別の一覧表を出せる形か確認）
... A75: ※ このシートは各社の申請ごとに1列使います。印刷して紙で回しても構いません。

Sheet やってはいけないこと
B2: 不正受給になる行為（絶対にやってはいけません）
B4: × 訓練機関からの返金・キャッシュバックを受け取る | C4: 名目を問わず不正受給になります。
B5: × 実際には訓練していないのに、行ったように書類を作る | C5: 出勤簿・賃金台帳・PCログイン記録の照合を求められることがあります。
B6: × 届け出ていない労働者の受講時間を計上する | C6: 計画届（様式第3-2号）に書いていない人の時間は入れられません。
B7: × 同一事業所で同じ定額制サービスを重複申請する | C7: グループ内で申請が重なっていないか、必ず突き合わせてください。
B8: × 受講料を受講者本人に負担させる | C8: 後から会社が返金しても認められません。会社が全額負担してください。
B10: 見つかった場合 | C10: 受給額の全額返還＋延滞金＋違約金（返還額の2割に相当する額）＋事業主名・代表者名・役員名等の公表。最悪の場合は刑事告訴の対象になります。さらに、不正受給の決定日から5年間、この助成金に限らず雇用関係助成金の全般が受給できなくなります（全額返納していない場合はさらに延長）。グループの1社の不正が、その会社のキャリアアップ助成金なども5年間止めます。※延滞金の率は資料に「3%」とありますが、点検で「年5%」とする情報も出たため、率は労働局に確認してください。
B12: よくある申請ミス
B14: ・計画届の提出期限を間違える | C14: 「訓練開始日の6か月前〜1か月前」は通学制の場合。定額制サービスは「契約開始日の1か月前まで」です。
B15: ・受講予定者の届出漏れ | C15: 様式第3-2号に書いていない人は後から追加できません。受講させる予定の全員を最初に届け出てください。
B16: ・10時間要件を確認しないまま終わる | C16: 訓練が終わってから10時間未満と分かっても対象外です。定期的に受講状況を確認してください。
B17: ・訓練機関の承諾書をもらい忘れる | C17: 様式第12号は訓練機関の承諾が必要です。直前に頼むと間に合わないことがあります。
B18: ・支給申請期限を過ぎる | C18: 訓練終了日の翌日から2か月以内。複数社を見ているときは、各社の訓練終了日を一覧で管理してください。
B19: ・提出後に書類を直そうとする | C19: 一度出した書類の差し替え・訂正は原則できません。出す前に確認してください。
B20: ・労働保険料の未納 | C20: 支給申請年度の前年度以前に未納があると受給できません。各社の納付状況を確認してください。
B23: この資料について | C23: 紙資料（自称根拠＝厚労省 詳細パンフレット・支給要項 R8.5.14版）を2026年9月15日に読み取って作成。厚労省の一次情報とは未突合です。より新しい「令和8年8月3日改正版」が存在する可能性があります。提出前に必ず管轄の都道府県労働局またはハローワークで最新版を確認してください。

Sheet 事前スクリーニング
A1: 事前スクリーニング 計画届を出す前に、各社にこの質問を当ててください
A2: 確認すること | B2: なぜ必要か | C2: =IF(期限一覧!A3="","（会社1）",期限一覧!A3) | D2: =IF(期限一覧!A4="","（会社2）",期限一覧!A4) | E2: =IF(期限一覧!A5="","（会社3）",期限一覧!A5) | F2: =IF(期限一覧!A6="","（会社4）",期限一覧!A6) | G2: =IF(期限一覧!A7="","（会社5）",期限一覧!A7) | H2: =IF(期限一覧!A8="","（会社6）",期限一覧!A8) | I2: =IF(期限一覧!A9="","（会社7）",期限一覧!A9) | J2: =IF(期限一覧!A10="","（会社8）",期限一覧!A10)
A3: 支給申請日の前日から1年前までの間に、労働関係法令の違反がありませんか | B3: 労基署の是正勧告・指導を受けていると不支給になります。計画届が通っても支給申請で落ちます。
A4: 過去に雇用関係助成金の不正受給をしていませんか | B4: 不正受給の決定日から5年間、雇用関係助成金の全般が受給できません。
A5: 労働保険料の未納がありませんか | B5: 判定は「支給申請日の属する年度の前年度より前」の保険年度とされます。表現に幅があるため労働局に確認してください。
A6: 性風俗関連営業・接待を伴う飲食等営業、またはその一部を受託する営業ではありませんか | B6: 判定は業種コードではなく実態です。
A7: 事業主または役員等が暴力団と関わりを持っていませんか | B7: 役員名簿をもとに確認します。
A8: 事業主都合の解雇をしていませんか | B8: コースによって要件の有無が異なります。本コースに課されるかは労働局に確認してください。※要確認
A9: 企業全体（事業所単位ではなく企業単位）で中小企業に当たりますか | B9: 資本金「または」労働者数のどちらかを満たせば中小です。両方必要ではありません。判定業種は登記の目的ではなく主たる事業の実態で見ます。
A10: 職業能力開発推進者を選任し、事業内職業能力開発計画を全従業員に周知していますか | B10: 周知の記録（掲示・配布・イントラ掲載等）を残してください。
A11: 定額制サービスを各社がそれぞれ契約し、各社の口座から支払っていますか | B11: 親会社の一括契約だと、子会社が自社の支払を証明できず対象外になるおそれがあります。
A12: 定額制サービスのアカウントが雇用保険適用事業所ごとに分かれていますか | B12: 訓練機関が発行する「10時間以上の者の一覧表」は雇用保険適用事業所ごとに作られる必要があります。契約時点で決まるため、後から直せません。
A13: 対象外講座（趣味・教養等）の割合を訓練機関に確認しましたか | B13: 全講座数に占める割合で判定します。ちょうど5割のときの扱いが資料と官の表現で逆になるため、境界線上なら労働局に確認してください。
A15: ※ 1つでも NG があると、計画届が通っても支給申請の段階で不支給になります。
A16: ※ この一覧は「支給要件確認申立書（共通要領様式第1号）」で申し立てる内容をもとにしています。実際の様式を見ながら各社に当ててください。

Sheet 税務の注意
B2: 税務の注意 ─ 助成金は「もらって終わり」ではありません
B3: ※ 一般的な制度の説明です。個別の税額計算・申告判断は必ず各社の顧問税理士にご確認ください。この内容も一次情報（国税庁）とは未突合です。
B5: 助成金には税金がかかります | C5: 「補助金だから非課税」は誤りです。本コースは経費助成のみで固定資産を買うための補助金ではないため、圧縮記帳（法人税法42条）による課税の繰り延べが使えません。受給額はそのまま課税所得を押し上げます。75%で受給しても、課税される分だけ手取りは下回ります。
B6: 「入金日に雑収入」で処理しないでください | C6: 助成金は原則として支給決定があった事業年度の収益です。前期に支給決定・翌期に入金なら、前期に未収入金として計上します。さらに本コースは「事前に計画届を出す経費補填の助成金」なので、受講料が発生した事業年度に対応させる取扱い（法人税基本通達2-1-42）が適用される可能性があります。
B7: 各社の決算期はバラバラです | C7: 同じ訓練・同じ支給決定日でも、会社ごとに計上すべき事業年度が変わります。全社まとめて同じ処理をしないでください。訓練終了から支給決定まで数か月かかるため、決算期をまたぐ場合は申告前に顧問税理士へ確認してください。
B8: 消費税：助成金は不課税です | C8: 助成金の受取に消費税はかかりません。「雑収入」で入力するとき、会計ソフトの課税区分が課税売上のままになっていないか各社ごとに確認してください。誤ると納税額と課税売上割合が狂います。複数社をまとめて入力すると横並びで間違えます。
B9: 受講料の消費税は減らされません | C9: 助成金を受けても、その助成金を充てた受講料の仕入税額控除は制限されません（「特定収入」の調整は公益法人等が対象で、普通の会社には適用されません）。ここは安心してよい部分です。
B10: インボイス：訓練機関の登録番号を確認 | C10: 訓練機関が適格請求書発行事業者でない場合、受講料の消費税は全額控除できません。経過措置の控除割合が令和8年10月1日に切り替わります。契約書・請求書にTから始まる13桁の登録番号があるか、契約前に確認してください。各社が簡易課税・2割特例なら影響しません。
B11: 各社がそれぞれ契約し、自社の口座から払う | C11: 親会社が一括契約して子会社に請求しないと、(a)子会社が自社負担を証明できず助成対象外になるおそれ (b)親会社で寄附金と認定され原則として損金にならない（100%グループでも解消しません）、の両方が起きます。子会社が仕入税額控除をするには子会社宛ての適格請求書（または立替金精算書＋写し）が必要です。
B12: 「会社が全額負担」は税務上も原則問題ありません | C12: 業務遂行上の必要に基づき、職務に直接必要な知識・技能を習得させるための適正な額の費用であれば、給与として課税されません（所得税基本通達36-29の2）。業務命令として労働時間内に行い、通常の賃金を払っていること自体が、その証拠資料になります。
B13: ただし趣味・教養の講座は別です | C13: 定額制サービスには趣味・教養の講座が含まれます（助成金は5割未満なら可）。しかし税務は「職務に直接必要」を求めるため、趣味・教養講座の受講分は現物給与と評価される可能性があります。受講させる講座を業務命令で具体的に指定し、その記録を残してください。
B14: 年払いサブスクの一括損金は決め打ちしない | C14: 短期前払費用の特例（法人税基本通達2-2-14）は「等質等量のサービスが継続的に提供される」ことが要件です。定額制eラーニングは月ごとに受講量が大きく変動する（10時間要件のため特定月に集中受講する）ため、当然に使えるとは限りません。グループで処理方針を統一してください（継続適用が要件です）。
B15: 保管：税務のほうが長い | C15: 助成金は支給決定後5年ですが、法人税の帳簿書類は原則7年、赤字の事業年度は10年です。5年で捨てないでください。また受講料の請求書・領収書をメールやWebダウンロードで受け取る場合は電子取引に当たり、データのまま保存する義務があります（印刷しただけでは要件を満たしません）。
B16: 返還が生じた場合 | C16: すでに収益計上した助成金をいつ戻すか（修正申告になるか）は個別判断です。また違約金や延滞金は損金にならない可能性があり、その場合の実質負担は返還額＋αより重くなります。返還が発生したらすぐ顧問税理士に相談してください。

Sheet 要確認リスト
A1: 労働局・税理士に確認すべきこと 確認したら「確認日」と「回答」を埋めてください
A2: 優先 | B2: 確認すること | C2: なぜ | D2: 確認先 | E2: 確認日 | F2: 回答・結論
A3: 最優先 | B3: 支給要領・パンフレットの最新版は何年何月版か（令和8年8月3日改正版の有無と内容） | C3: この資料はR8.5.14版に基づく。8/3以降に計画届を出す案件には前提が当てはまらないおそれ | D3: 労働局／厚労省サイト
A4: 最優先 | B4: 経費助成の上限額（1人あたり／1事業所あたり／1年度あたり／定額制固有）と、75%を掛ける順序 | C4: 資料に記載がない。契約額×75%で経営者に提示すると期待値を誤らせる | D4: 労働局
A5: 最優先 | B5: 1労働者1年度あたりの申請回数の上限。eラーニングの年1回制限が定額制にも及ぶか | C5: 情報が割れている。複数回申請を前提に動くと2回目以降が全額不支給になり得る | D5: 労働局
A6: 最優先 | B6: 汎用的なAI・DX・GX研修が対象外になったか。講座選定の基準 | C6: 定額制は受け放題のため汎用講座が主力になりがち。計画届段階で立証を作り込む必要 | D6: 労働局
A7: 最優先 | B7: 事業展開等実施計画に認定経営革新等支援機関の確認が必要か | C7: 必要なら工程が1本増え、「契約初日の1か月前」の期限設計が破綻する | D7: 労働局
A8: 高 | B8: 計画届の提出期限の両端（最早提出日はあるか。6か月前より早いと受理されないか） | C8: 情報が割れている。期限を外すとその訓練は全損 | D8: 労働局
A9: 高 | B9: 事業所確認票は様式第13号か、様式第14-1号か | C9: 資料内で矛盾している。このままでは半分の確率で誤った様式を使う | D9: 労働局／様式一覧
A10: 高 | B10: 不正受給の延滞金の率（3%か年5%か）と、不支給期間（5年か） | C10: 資料は3%。点検で年5%とする情報も出た | D10: 労働局
A11: 高 | B11: 賃金要件・資格等手当要件の加算率（+15%か）と、設備投資加算の要件・加算率 | C11: 資料は「さらに加算あり」としか書いていない。加算は計画届段階で意思表示しないと後から取れないのが通例 | D11: 労働局
A12: 高 | B12: 本コースに事業主都合解雇の要件が課されるか | C12: コースにより有無が異なる | D12: 労働局
A13: 中 | B13: 労働保険料の要件は「前年度以前」か「前年度より前」か。除外規定の文言 | C13: 前年度分を含むかで結論が逆になる | D13: 労働局
A14: 中 | B14: 5割要件で、対象外講座がちょうど5割のときはどちらか | C14: 資料と官の表現で結論が逆になる | D14: 労働局
... A22: 中 | B22: 訓練機関が適格請求書発行事業者か。各社の課税方式（本則／簡易／2割特例） | C22: 経過措置の控除割合が令和8年10月1日に切り替わる | D22: 訓練機関／顧問税理士
B24: ※ この一覧は、社労士・税理士・診断士の3観点でこの資料を点検したときに「一次情報で確認できなかった」項目です。
B25: ※ 厚生労働省・国税庁のサイトに接続できない環境で点検したため、条文やパンフレットの原文は読めていません。
